[
  {
    "Code": "190",
    "Description": "Geriatrische revalidatiezorg"
  },
  {
    "Code": "191",
    "Description": "Herstelgerichte behandeling met verpleging en verzorging"
  },
  {
    "Code": "750",
    "Description": "Beschut wonen met enige begeleiding"
  },
  {
    "Code": "751",
    "Description": "Beschut wonen met begeleiding en verzorging"
  },
  {
    "Code": "752",
    "Description": "Beschut wonen met begeleiding en intensieve verzorging"
  },
  {
    "Code": "753",
    "Description": "Beschut wonen met intensieve begeleiding en uitgebreide verzorging"
  },
  {
    "Code": "754",
    "Description": "Beschermd wonen met intensieve dementiezorg"
  },
  {
    "Code": "755",
    "Description": "Beschermd wonen met intensieve verzorging en verpleging"
  },
  {
    "Code": "756",
    "Description": "Beschermd wonen met zeer intensieve zorg, vanwege specifieke aandoeningen, met nadruk op begeleiding"
  },
  {
    "Code": "757",
    "Description": "Beschermd wonen met zeer intensieve zorg, vanwege specifieke aandoeningen, met de nadruk op verzorging/verpleging"
  },
  {
    "Code": "758",
    "Description": "Herstelgerichte behandeling met verpleging en verzorging"
  },
  {
    "Code": "759",
    "Description": "Beschermd verblijf met intensieve palliatief-terminale zorg"
  },
  {
    "Code": "760",
    "Description": "Beschermd wonen met begeleiding"
  },
  {
    "Code": "762",
    "Description": "Gestructureerd beschermd wonen met uitgebreide begeleiding"
  },
  {
    "Code": "764",
    "Description": "Beschermd wonen met intensieve begeleiding"
  },
  {
    "Code": "766",
    "Description": "Voortgezet verblijf met intensieve begeleiding en verzorging"
  },
  {
    "Code": "768",
    "Description": "Voortgezet verblijf met intensieve begeleiding en gedragsregulering"
  },
  {
    "Code": "770",
    "Description": "Voortgezet verblijf met intensieve begeleiding en intensieve verpleging en verzorging"
  },
  {
    "Code": "772",
    "Description": "Beveiligd voortgezet verblijf vanwege extreme gedragsproblematiek met zeer intensieve begeleiding"
  },
  {
    "Code": "780",
    "Description": "Wonen met enige behandeling en begeleiding"
  },
  {
    "Code": "781",
    "Description": "Wonen met behandeling en begeleiding"
  },
  {
    "Code": "782",
    "Description": "Wonen met intensieve behandeling en begeleiding, kleine groep"
  },
  {
    "Code": "783",
    "Description": "Wonen met zeer intensieve behandeling en begeleiding"
  },
  {
    "Code": "784",
    "Description": "Besloten wonen met zeer intensieve behandeling en begeleiding"
  },
  {
    "Code": "790",
    "Description": "Behandeling in een SGLVG-behandelcentrum"
  },
  {
    "Code": "800",
    "Description": "Wonen met enige begeleiding"
  },
  {
    "Code": "802",
    "Description": "Wonen met begeleiding"
  },
  {
    "Code": "804",
    "Description": "Wonen met begeleiding en verzorging"
  },
  {
    "Code": "806",
    "Description": "Wonen met begeleiding en intensieve verzorging"
  },
  {
    "Code": "808",
    "Description": "Wonen met begeleiding en zeer intensieve verzorging"
  },
  {
    "Code": "810",
    "Description": "Wonen met intensieve begeleiding, verzorging en gedragsregulering"
  },
  {
    "Code": "812",
    "Description": "(Besloten) wonen met zeer intensieve begeleiding, verzorging en gedragsregulering"
  },
  {
    "Code": "814",
    "Description": "Wonen met begeleiding en volledige verzorging en verpleging"
  },
  {
    "Code": "820",
    "Description": "Wonen met enige begeleiding en enige verzorging"
  },
  {
    "Code": "822",
    "Description": "Wonen met begeleiding en enige verzorging"
  },
  {
    "Code": "824",
    "Description": "Wonen met enige begeleiding en verzorging"
  },
  {
    "Code": "826",
    "Description": "Wonen met begeleiding en verzorging"
  },
  {
    "Code": "828",
    "Description": "Wonen met begeleiding en intensieve verzorging"
  },
  {
    "Code": "830",
    "Description": "Wonen met intensieve begeleiding en intensieve verzorging"
  },
  {
    "Code": "832",
    "Description": "Wonen met zeer intensieve begeleiding en zeer intensieve verzorging"
  },
  {
    "Code": "840",
    "Description": "Wonen met enige begeleiding en enige verzorging"
  },
  {
    "Code": "842",
    "Description": "Wonen met begeleiding en enige verzorging"
  },
  {
    "Code": "844",
    "Description": "Wonen met intensieve begeleiding en verzorging"
  },
  {
    "Code": "846",
    "Description": "Wonen met intensieve begeleiding en intensieve verzorging"
  },
  {
    "Code": "848",
    "Description": "Wonen met zeer intensieve begeleiding en zeer intensieve verzorging"
  },
  {
    "Code": "850",
    "Description": "Wonen met begeleiding en enige verzorging"
  },
  {
    "Code": "852",
    "Description": "Wonen met intensieve begeleiding en verzorging"
  },
  {
    "Code": "854",
    "Description": "Wonen met intensieve begeleiding en intensieve verzorging"
  },
  {
    "Code": "856",
    "Description": "Wonen met intensieve begeleiding en enige verzorging"
  },
  {
    "Code": "860",
    "Description": "Voortgezet verblijf met beleiding"
  },
  {
    "Code": "862",
    "Description": "Voortgezet verblijf met structuur en uitgebreide begeleiding"
  },
  {
    "Code": "864",
    "Description": "Voortgezet verblijf met intensieve begeleiding"
  },
  {
    "Code": "866",
    "Description": "Gestructureerd beschermd wonen met intensieve begeleiding en verzorging"
  },
  {
    "Code": "868",
    "Description": "Beschermd wonen met intensieve begeleiding en gedragsregulering"
  },
  {
    "Code": "870",
    "Description": "Beschermd wonen met intensieve begeleiding en intensieve verpleging en verzorging"
  },
  {
    "Code": "998",
    "Description": "Onbepaald zorgzwaartepakket"
  },
  {
    "Code": "999",
    "Description": "Partnerverblijf"
  }
]